drpangloss/__init__.py
drpangloss/grid_fit.py
drpangloss/models.py
drpangloss/models_old.py
drpangloss/oifits_implaneia.py
drpangloss/plotting.py
drpangloss/savefits.py
drpangloss-0.0.2.dist-info/licenses/LICENSE
drpangloss-0.0.2.dist-info/METADATA
drpangloss-0.0.2.dist-info/WHEEL
drpangloss-0.0.2.dist-info/top_level.txt
drpangloss-0.0.2.dist-info/RECORD
