Metadata-Version: 2.4
Name: drpangloss
Version: 0.0.2
Summary: Python package to fit interferometric data, accelerated using Jax.
Author-email: Benjamin Pope <b.pope@uq.edu.au>, Dori Blakely <blakelyd@uvic.ca>
Project-URL: repository, https://github.com/benjaminpope/drpangloss
Keywords: python,optics,machine-learning,jax,autodiff,differentiable,diffraction,simulation,telescope,drpangloss
Classifier: Programming Language :: Python :: 3
Classifier: Operating System :: OS Independent
Requires-Python: >=3.11
License-File: LICENSE
Requires-Dist: jax
Requires-Dist: jaxlib
Requires-Dist: zodiax
Requires-Dist: numpy
Requires-Dist: matplotlib
Requires-Dist: numpyro
Requires-Dist: tensorflow-probability
Requires-Dist: astropy
Requires-Dist: tqdm
Requires-Dist: optimistix
Requires-Dist: scipy
Requires-Dist: astroquery
Requires-Dist: pyoifits
Dynamic: license-file
